{
    "snippet": {
        "5460000": {
            "timestamp": 1327526664.388996, 
            "secret": "rRIsrkzyHYhCUuqy"
        }, 
        "5430000": {
            "timestamp": 1327526664.388996, 
            "secret": "MHCMxpujtoDPrzeM"
        }, 
        "6390000": {
            "timestamp": 1327526673.194495, 
            "secret": "VxHLVqbRGwVCblTk"
        }
    }, 
    "review": {
        "5430000": {
            "timestamp": 1327526664.388996, 
            "secret": "zObMNociNqvSGezH"
        }
    }
}